[
  {
    "TaskNodeId": "TASK_APEX_001_OVERHEAD",
    "TenantId": "TENANT001",
    "ContractId": "CONTRACT_APEX_001",
    "ParentTaskNodeId": null,
    "NodeType": "TaskArea",
    "Title": "Indirect/Overhead",
    "Description": "G&A, Admin, Training, Leave and other non-direct work",
    "Status": "InProgress",
    "ScopedHours": 2000,
    "AllocatedHours": 2000,
    "SortOrder": 0,
    "CreatedByUserId": "USER_APEX_PM1",
    "CreatedUtc": "2025-01-15T11:00:00Z",
    "UpdatedByUserId": "USER_APEX_PM1",
    "UpdatedUtc": "2025-01-15T11:00:00Z"
  },
  {
    "TaskNodeId": "TASK_APEX_001_AREA1",
    "TenantId": "TENANT001",
    "ContractId": "CONTRACT_APEX_001",
    "ParentTaskNodeId": null,
    "NodeType": "TaskArea",
    "Title": "Network Security Assessment",
    "Description": "Comprehensive security assessment of DOD network infrastructure",
    "Status": "InProgress",
    "ScopedHours": 1200,
    "AllocatedHours": 1200,
    "SortOrder": 1,
    "CreatedByUserId": "USER_APEX_PM1",
    "CreatedUtc": "2025-01-15T11:10:00Z",
    "UpdatedByUserId": "USER_APEX_PM1",
    "UpdatedUtc": "2025-01-15T11:10:00Z"
  },
  {
    "TaskNodeId": "TASK_APEX_001_T1",
    "TenantId": "TENANT001",
    "ContractId": "CONTRACT_APEX_001",
    "ParentTaskNodeId": "TASK_APEX_001_AREA1",
    "NodeType": "Task",
    "Title": "Initial Vulnerability Scan",
    "Description": "Run automated vulnerability scanning tools across all network segments",
    "Status": "Done",
    "ScopedHours": 120,
    "AllocatedHours": 120,
    "SortOrder": 0,
    "CreatedByUserId": "USER_APEX_LEAD1",
    "CreatedUtc": "2025-01-16T08:00:00Z",
    "UpdatedByUserId": "USER_APEX_WORKER1",
    "UpdatedUtc": "2025-02-01T15:30:00Z"
  },
  {
    "TaskNodeId": "TASK_APEX_001_T2",
    "TenantId": "TENANT001",
    "ContractId": "CONTRACT_APEX_001",
    "ParentTaskNodeId": "TASK_APEX_001_AREA1",
    "NodeType": "Task",
    "Title": "Penetration Testing",
    "Description": "Conduct manual penetration testing on critical systems",
    "Status": "InProgress",
    "ScopedHours": 240,
    "AllocatedHours": 240,
    "SortOrder": 1,
    "CreatedByUserId": "USER_APEX_LEAD1",
    "CreatedUtc": "2025-01-16T08:15:00Z",
    "UpdatedByUserId": "USER_APEX_WORKER2",
    "UpdatedUtc": "2025-02-12T10:00:00Z"
  },
  {
    "TaskNodeId": "TASK_APEX_001_T3",
    "TenantId": "TENANT001",
    "ContractId": "CONTRACT_APEX_001",
    "ParentTaskNodeId": "TASK_APEX_001_AREA1",
    "NodeType": "Task",
    "Title": "Security Report Compilation",
    "Description": "Compile findings into comprehensive security assessment report",
    "Status": "NotStarted",
    "ScopedHours": 160,
    "AllocatedHours": 160,
    "SortOrder": 2,
    "CreatedByUserId": "USER_APEX_LEAD1",
    "CreatedUtc": "2025-01-16T08:30:00Z",
    "UpdatedByUserId": "USER_APEX_LEAD1",
    "UpdatedUtc": "2025-01-16T08:30:00Z"
  },
  {
    "TaskNodeId": "TASK_APEX_001_AREA2",
    "TenantId": "TENANT001",
    "ContractId": "CONTRACT_APEX_001",
    "ParentTaskNodeId": null,
    "NodeType": "TaskArea",
    "Title": "Firewall Modernization",
    "Description": "Upgrade and configure next-generation firewalls",
    "Status": "InProgress",
    "ScopedHours": 800,
    "AllocatedHours": 800,
    "SortOrder": 2,
    "CreatedByUserId": "USER_APEX_PM1",
    "CreatedUtc": "2025-01-15T11:30:00Z",
    "UpdatedByUserId": "USER_APEX_PM1",
    "UpdatedUtc": "2025-01-15T11:30:00Z"
  },
  {
    "TaskNodeId": "TASK_APEX_001_T4",
    "TenantId": "TENANT001",
    "ContractId": "CONTRACT_APEX_001",
    "ParentTaskNodeId": "TASK_APEX_001_AREA2",
    "NodeType": "Task",
    "Title": "Firewall Hardware Installation",
    "Description": "Install new firewall appliances at all sites",
    "Status": "InProgress",
    "ScopedHours": 200,
    "AllocatedHours": 200,
    "SortOrder": 0,
    "CreatedByUserId": "USER_APEX_LEAD1",
    "CreatedUtc": "2025-01-20T09:00:00Z",
    "UpdatedByUserId": "USER_APEX_WORKER3",
    "UpdatedUtc": "2025-02-10T14:00:00Z"
  },
  {
    "TaskNodeId": "TASK_APEX_001_T5",
    "TenantId": "TENANT001",
    "ContractId": "CONTRACT_APEX_001",
    "ParentTaskNodeId": "TASK_APEX_001_AREA2",
    "NodeType": "Task",
    "Title": "Firewall Configuration & Rules",
    "Description": "Configure firewall rules and policies per security requirements",
    "Status": "Blocked",
    "ScopedHours": 150,
    "AllocatedHours": 150,
    "SortOrder": 1,
    "CreatedByUserId": "USER_APEX_LEAD1",
    "CreatedUtc": "2025-01-20T09:15:00Z",
    "UpdatedByUserId": "USER_APEX_WORKER3",
    "UpdatedUtc": "2025-02-13T11:00:00Z"
  },
  {
    "TaskNodeId": "TASK_APEX_002_AREA1",
    "TenantId": "TENANT001",
    "ContractId": "CONTRACT_APEX_002",
    "ParentTaskNodeId": null,
    "NodeType": "TaskArea",
    "Title": "Data Migration Planning",
    "Description": "Plan the migration of legacy health records to new system",
    "Status": "InProgress",
    "ScopedHours": 600,
    "AllocatedHours": 600,
    "SortOrder": 0,
    "CreatedByUserId": "USER_APEX_PM1",
    "CreatedUtc": "2025-02-01T10:00:00Z",
    "UpdatedByUserId": "USER_APEX_PM1",
    "UpdatedUtc": "2025-02-01T10:00:00Z"
  },
  {
    "TaskNodeId": "TASK_APEX_002_T1",
    "TenantId": "TENANT001",
    "ContractId": "CONTRACT_APEX_002",
    "ParentTaskNodeId": "TASK_APEX_002_AREA1",
    "NodeType": "Task",
    "Title": "Legacy System Analysis",
    "Description": "Analyze current VA health records system and data structure",
    "Status": "Done",
    "ScopedHours": 80,
    "AllocatedHours": 80,
    "SortOrder": 0,
    "CreatedByUserId": "USER_APEX_LEAD1",
    "CreatedUtc": "2025-02-01T11:00:00Z",
    "UpdatedByUserId": "USER_APEX_WORKER1",
    "UpdatedUtc": "2025-02-10T16:00:00Z"
  },
  {
    "TaskNodeId": "TASK_APEX_002_T2",
    "TenantId": "TENANT001",
    "ContractId": "CONTRACT_APEX_002",
    "ParentTaskNodeId": "TASK_APEX_002_AREA1",
    "NodeType": "Task",
    "Title": "Migration Strategy Document",
    "Description": "Create comprehensive migration strategy and timeline",
    "Status": "InProgress",
    "ScopedHours": 120,
    "AllocatedHours": 120,
    "SortOrder": 1,
    "CreatedByUserId": "USER_APEX_LEAD1",
    "CreatedUtc": "2025-02-01T11:15:00Z",
    "UpdatedByUserId": "USER_APEX_WORKER2",
    "UpdatedUtc": "2025-02-14T09:30:00Z"
  },
  {
    "TaskNodeId": "TASK_MERID_001_AREA1",
    "TenantId": "TENANT002",
    "ContractId": "CONTRACT_MERID_001",
    "ParentTaskNodeId": null,
    "NodeType": "TaskArea",
    "Title": "Cloud Infrastructure Setup",
    "Description": "Configure AWS cloud infrastructure for GSA",
    "Status": "InProgress",
    "ScopedHours": 400,
    "AllocatedHours": 400,
    "SortOrder": 0,
    "CreatedByUserId": "USER_MERID_PM1",
    "CreatedUtc": "2025-02-15T10:00:00Z",
    "UpdatedByUserId": "USER_MERID_PM1",
    "UpdatedUtc": "2025-02-15T10:00:00Z"
  },
  {
    "TaskNodeId": "TASK_MERID_001_T1",
    "TenantId": "TENANT002",
    "ContractId": "CONTRACT_MERID_001",
    "ParentTaskNodeId": "TASK_MERID_001_AREA1",
    "NodeType": "Task",
    "Title": "VPC Configuration",
    "Description": "Set up Virtual Private Cloud with proper subnets and security groups",
    "Status": "InProgress",
    "ScopedHours": 80,
    "AllocatedHours": 80,
    "SortOrder": 0,
    "CreatedByUserId": "USER_MERID_WORKER1",
    "CreatedUtc": "2025-02-15T11:00:00Z",
    "UpdatedByUserId": "USER_MERID_WORKER1",
    "UpdatedUtc": "2025-02-15T11:00:00Z"
  },
  {
    "TaskNodeId": "TASK_MERID_001_T2",
    "TenantId": "TENANT002",
    "ContractId": "CONTRACT_MERID_001",
    "ParentTaskNodeId": "TASK_MERID_001_AREA1",
    "NodeType": "Task",
    "Title": "Load Balancer Setup",
    "Description": "Configure application load balancers for high availability",
    "Status": "NotStarted",
    "ScopedHours": 60,
    "AllocatedHours": 60,
    "SortOrder": 1,
    "CreatedByUserId": "USER_MERID_WORKER1",
    "CreatedUtc": "2025-02-15T11:15:00Z",
    "UpdatedByUserId": "USER_MERID_WORKER1",
    "UpdatedUtc": "2025-02-15T11:15:00Z"
  }
]
